skl2onnx/__init__.py
skl2onnx/__main__.py
skl2onnx/_parse.py
skl2onnx/_supported_operators.py
skl2onnx/convert.py
skl2onnx-1.19.0.dist-info/licenses/LICENSE
skl2onnx-1.19.0.dist-info/licenses/NOTICE
skl2onnx-1.19.0.dist-info/METADATA
skl2onnx-1.19.0.dist-info/WHEEL
skl2onnx-1.19.0.dist-info/top_level.txt
skl2onnx-1.19.0.dist-info/RECORD
