Metadata-Version: 2.4
Name: skl2onnx
Version: 1.19.0
Summary: Convert scikit-learn models to ONNX
Author-email: ONNX Contributors <onnx-technical-discuss@lists.lfaidata.foundation>
License: Apache License v2.0
Project-URL: Homepage, https://github.com/onnx/sklearn-onnx
Classifier: Development Status :: 4 - Beta
Classifier: Environment :: Console
Classifier: Intended Audience :: Developers
Classifier: Operating System :: MacOS :: MacOS X
Classifier: Operating System :: Microsoft :: Windows
Classifier: Programming Language :: Python
Classifier: Programming Language :: Python :: 3.8
Classifier: Programming Language :: Python :: 3.9
Classifier: Programming Language :: Python :: 3.10
Classifier: Programming Language :: Python :: 3.11
Classifier: Programming Language :: Python :: 3.12
Classifier: Programming Language :: Python :: 3.13
Classifier: License :: OSI Approved :: Apache Software License
Requires-Python: >=3.8
License-File: LICENSE
License-File: NOTICE
Requires-Dist: onnx>=1.2.1
Requires-Dist: scikit-learn>=1.1
Dynamic: license-file
